README.rst
setup.py
packmap/__init__.py
packmap/cli.py
packmap/env.py
packmap/finder.py
packmap.egg-info/PKG-INFO
packmap.egg-info/SOURCES.txt
packmap.egg-info/dependency_links.txt
packmap.egg-info/entry_points.txt
packmap.egg-info/requires.txt
packmap.egg-info/top_level.txt