Metadata-Version: 1.1
Name: packmap
Version: 0.0.1
Summary: PackMap discovers all dependencies for a specificPython package
Home-page: https://github.com/jmvrbanac/PackMap
Author: John Vrbanac
Author-email: john.vrbanac@linux.com
License: Apache License 2.0
Keywords: discover package dependencies graph dependency requirement
Platform: UNKNOWN
Classifier: Development Status :: 3 - Alpha
Classifier: Intended Audience :: Developers
Classifier: License :: OSI Approved :: Apache Software License
Classifier: Programming Language :: Python :: 2.7
Classifier: Operating System :: POSIX :: Linux
Classifier: Environment :: Console
Classifier: Topic :: Utilities
